fixrobot/__init__.py
fixrobot/fixrobot.py
fixrobot/tests/FIX42RobotUnitTest_ShouldFail.py
fixrobot/tests/FIX42RobotUnitTest_ShouldPass.py
fixrobot/tests/FIX50RobotUnitTest_ShouldFail.py
fixrobot/tests/FIX50RobotUnitTest_ShouldPass.py
fixrobot/tests/__init__.py
fixrobot/tests/conftest.py
fixrobot/tests/runPyTest.bat
fixrobot/tests/runPyTest.sh
fixrobot/tests/runPyTestAll.bat
fixrobot/tests/runPyTestAll.sh
fixrobot/tests/runTest.bat
fixrobot/tests/runTest.sh
fixrobot/tests/runTestAll.bat
fixrobot/tests/runTestAll.sh
fixrobot/tests/test_FIX42RobotPyTest_ShouldFail.py
fixrobot/tests/test_FIX42RobotPyTest_ShouldPass.py
fixrobot/tests/test_FIX50RobotPyTest_ShouldFail.py
fixrobot/tests/test_FIX50RobotPyTest_ShouldPass.py
fixrobot-1.0.3.dist-info/LICENSE
fixrobot-1.0.3.dist-info/METADATA
fixrobot-1.0.3.dist-info/WHEEL
fixrobot-1.0.3.dist-info/entry_points.txt
fixrobot-1.0.3.dist-info/top_level.txt
fixrobot-1.0.3.dist-info/RECORD
