Metadata-Version: 2.1
Name: fixrobot
Version: 1.0.3
Summary: A useful module to test FIX connectivity and FIX engines. Usage: import fixrobot
Home-page: https://github.com/quickfixrobot
Author: Anand P Subramanian
Author-email: quickfixrobot@gmail.com
License: MIT
Keywords: one,two
Classifier: Framework :: Pytest
Classifier: Programming Language :: Python :: 3
Requires-Python: >=3.4
License-File: LICENSE
Requires-Dist: wheel
Requires-Dist: configparser
Requires-Dist: pytest
Provides-Extra: pdf
Requires-Dist: ReportLab (>=1.2) ; extra == 'pdf'
Requires-Dist: RXP ; extra == 'pdf'
Provides-Extra: rest
Requires-Dist: docutils (>=0.3) ; extra == 'rest'
Requires-Dist: pack (==1.1,==1.3) ; extra == 'rest'
